<?xml version="1.0"?>
<clause number="12.1.3" title="Elementos de un arreglo">
  <paragraph>Los elementos de un arreglo comienzan a existir cuando es creada una instancia del arreglo, y cesan de existir cuando no hay referencias a la instancia del arreglo. </paragraph>
  <paragraph>El valor inicial de cada elemento del arreglo es el valor por defecto (<hyperlink>12.2</hyperlink>) del tipo de los elementos del arreglo. </paragraph>
  <paragraph>Para los propósitos de comprobación de asignaciones definitivas, un elemento arreglo es considerado inicialmente asignado. </paragraph>
</clause>

<!-- traducción Carlos Parra, carlox_parra@yahoo.es -->
