<?xml version="1.0" encoding="utf-8"?>
<clause number="20.2.1" title="Métodos de interfaz">
  <paragraph>Los métodos de interfaz son declarados usando declaraciones-de-métodos-de-interfaz: <grammar_production><name><non_terminal where="20.2.1">declaración-de-método-de-interfaz</non_terminal></name> : <rhs><non_terminal where="24.2">atributos</non_terminal><opt/><keyword>new</keyword><opt/><non_terminal where="17.5">tipo-de-retorno</non_terminal><non_terminal where="9.4.2">identificador</non_terminal><terminal>(</terminal><non_terminal where="17.5.1">lista-de-parámetros-formales</non_terminal><opt/><terminal>)</terminal><terminal>;</terminal></rhs></grammar_production></paragraph>
  <paragraph>Los atributos, <non_terminal where="17.5">tipo-de-retorno</non_terminal>, identificador y <non_terminal where="17.5.1">lista-de-parámetros-formales</non_terminal> de una declaración de método de interfaz tienen el mismo significado que aquellos de una declaración de método en una clase (<hyperlink>17.5</hyperlink>). No está permitido que una declaración de método de interfaz especifique un cuerpo de método, y por lo tanto la declaración siempre termina con un punto y coma. </paragraph>
</clause>
<!-- traducción Rodolfo Campero, rodolfo.campero@gmail.com -->
